{
    "molssi_bse_magic": 1,
    "basisSetName": "aug-mcc-pV8Z",
    "basisSetDescription": "aug-mcc-pV8Z",
    "basisSetReferences": [
        "mielke2005a"
    ],
    "basisSetElements": {
        "1": {
            "elementElectronShells": [
                {
                    "shellFunctionType": "gto",
                    "shellHarmonicType": "spherical",
                    "shellRegion": "valence",
                    "shellAngularMomentum": [
                        0
                    ],
                    "shellExponents": [
                        "13940.8000000",
                        "3471.4300000",
                        "1903.1800000",
                        "623.2860000",
                        "290.3600000",
                        "126.5850000",
                        "44.6955000",
                        "16.0038000",
                        "6.0805600",
                        "2.4762200",
                        "1.0757100",
                        "0.4896820",
                        "0.2297860",
                        "0.1099655",
                        "0.0523230",
                        "0.0137700"
                    ],
                    "shellCoefficients": [
                        [
                            "0.00000301",
                            "0.00000544",
                            "0.00001785",
                            "0.00007195",
                            "0.00012055",
                            "0.00052527",
                            "0.00201384",
                            "0.00687086",
                            "0.02095415",
                            "0.05614039",
                            "0.13038113",
                            "0.25186989",
                            "0.35225121",
                            "0.26587036",
                            "0.05787678",
                            "0.00000000"
                        ],
                        [
                            "0.0000000",
                            "0.0000000",
                            "0.0000000",
                            "0.0000000",
                            "0.0000000",
                            "0.0000000",
                            "0.0000000",
                            "0.0000000",
                            "1.0000000",
                            "0.0000000",
                            "0.0000000",
                            "0.0000000",
                            "0.0000000",
                            "0.0000000",
                            "0.0000000",
                            "0.0000000"
                        ],
                        [
                            "0.0000000",
                            "0.0000000",
                            "0.0000000",
                            "0.0000000",
                            "0.0000000",
                            "0.0000000",
                            "0.0000000",
                            "0.0000000",
                            "0.0000000",
                            "1.0000000",
                            "0.0000000",
                            "0.0000000",
                            "0.0000000",
                            "0.0000000",
                            "0.0000000",
                            "0.0000000"
                        ],
                        [
                            "0.0000000",
                            "0.0000000",
                            "0.0000000",
                            "0.0000000",
                            "0.0000000",
                            "0.0000000",
                            "0.0000000",
                            "0.0000000",
                            "0.0000000",
                            "0.0000000",
                            "1.0000000",
                            "0.0000000",
                            "0.0000000",
                            "0.0000000",
                            "0.0000000",
                            "0.0000000"
                        ],
                        [
                            "0.0000000",
                            "0.0000000",
                            "0.0000000",
                            "0.0000000",
                            "0.0000000",
                            "0.0000000",
                            "0.0000000",
                            "0.0000000",
                            "0.0000000",
                            "0.0000000",
                            "0.0000000",
                            "1.0000000",
                            "0.0000000",
                            "0.0000000",
                            "0.0000000",
                            "0.0000000"
                        ],
                        [
                            "0.0000000",
                            "0.0000000",
                            "0.0000000",
                            "0.0000000",
                            "0.0000000",
                            "0.0000000",
                            "0.0000000",
                            "0.0000000",
                            "0.0000000",
                            "0.0000000",
                            "0.0000000",
                            "0.0000000",
                            "1.0000000",
                            "0.0000000",
                            "0.0000000",
                            "0.0000000"
                        ],
                        [
                            "0.0000000",
                            "0.0000000",
                            "0.0000000",
                            "0.0000000",
                            "0.0000000",
                            "0.0000000",
                            "0.0000000",
                            "0.0000000",
                            "0.0000000",
                            "0.0000000",
                            "0.0000000",
                            "0.0000000",
                            "0.0000000",
                            "1.0000000",
                            "0.0000000",
                            "0.0000000"
                        ],
                        [
                            "0.0000000",
                            "0.0000000",
                            "0.0000000",
                            "0.0000000",
                            "0.0000000",
                            "0.0000000",
                            "0.0000000",
                            "0.0000000",
                            "0.0000000",
                            "0.0000000",
                            "0.0000000",
                            "0.0000000",
                            "0.0000000",
                            "0.0000000",
                            "1.0000000",
                            "0.0000000"
                        ],
                        [
                            "0.0000000",
                            "0.0000000",
                            "0.0000000",
                            "0.0000000",
                            "0.0000000",
                            "0.0000000",
                            "0.0000000",
                            "0.0000000",
                            "0.0000000",
                            "0.0000000",
                            "0.0000000",
                            "0.0000000",
                            "0.0000000",
                            "0.0000000",
                            "0.0000000",
                            "1.0000000"
                        ]
                    ]
                },
                {
                    "shellFunctionType": "gto",
                    "shellHarmonicType": "spherical",
                    "shellRegion": "valence",
                    "shellAngularMomentum": [
                        1
                    ],
                    "shellExponents": [
                        "17.3691000",
                        "7.9252700",
                        "3.6161900",
                        "1.6500200",
                        "0.7528800",
                        "0.3435300",
                        "0.1567500",
                        "0.0528300"
                    ],
                    "shellCoefficients": [
                        [
                            "1.0000000",
                            "0.0000000",
                            "0.0000000",
                            "0.0000000",
                            "0.0000000",
                            "0.0000000",
                            "0.0000000",
                            "0.0000000"
                        ],
                        [
                            "0.0000000",
                            "1.0000000",
                            "0.0000000",
                            "0.0000000",
                            "0.0000000",
                            "0.0000000",
                            "0.0000000",
                            "0.0000000"
                        ],
                        [
                            "0.0000000",
                            "0.0000000",
                            "1.0000000",
                            "0.0000000",
                            "0.0000000",
                            "0.0000000",
                            "0.0000000",
                            "0.0000000"
                        ],
                        [
                            "0.0000000",
                            "0.0000000",
                            "0.0000000",
                            "1.0000000",
                            "0.0000000",
                            "0.0000000",
                            "0.0000000",
                            "0.0000000"
                        ],
                        [
                            "0.0000000",
                            "0.0000000",
                            "0.0000000",
                            "0.0000000",
                            "1.0000000",
                            "0.0000000",
                            "0.0000000",
                            "0.0000000"
                        ],
                        [
                            "0.0000000",
                            "0.0000000",
                            "0.0000000",
                            "0.0000000",
                            "0.0000000",
                            "1.0000000",
                            "0.0000000",
                            "0.0000000"
                        ],
                        [
                            "0.0000000",
                            "0.0000000",
                            "0.0000000",
                            "0.0000000",
                            "0.0000000",
                            "0.0000000",
                            "1.0000000",
                            "0.0000000"
                        ],
                        [
                            "0.0000000",
                            "0.0000000",
                            "0.0000000",
                            "0.0000000",
                            "0.0000000",
                            "0.0000000",
                            "0.0000000",
                            "1.0000000"
                        ]
                    ]
                },
                {
                    "shellFunctionType": "gto",
                    "shellHarmonicType": "spherical",
                    "shellRegion": "valence",
                    "shellAngularMomentum": [
                        2
                    ],
                    "shellExponents": [
                        "8.7070200",
                        "4.4505600",
                        "2.2748800",
                        "1.1628000",
                        "0.5943600",
                        "0.3038000",
                        "0.1044300"
                    ],
                    "shellCoefficients": [
                        [
                            "1.0000000",
                            "0.0000000",
                            "0.0000000",
                            "0.0000000",
                            "0.0000000",
                            "0.0000000",
                            "0.0000000"
                        ],
                        [
                            "0.0000000",
                            "1.0000000",
                            "0.0000000",
                            "0.0000000",
                            "0.0000000",
                            "0.0000000",
                            "0.0000000"
                        ],
                        [
                            "0.0000000",
                            "0.0000000",
                            "1.0000000",
                            "0.0000000",
                            "0.0000000",
                            "0.0000000",
                            "0.0000000"
                        ],
                        [
                            "0.0000000",
                            "0.0000000",
                            "0.0000000",
                            "1.0000000",
                            "0.0000000",
                            "0.0000000",
                            "0.0000000"
                        ],
                        [
                            "0.0000000",
                            "0.0000000",
                            "0.0000000",
                            "0.0000000",
                            "1.0000000",
                            "0.0000000",
                            "0.0000000"
                        ],
                        [
                            "0.0000000",
                            "0.0000000",
                            "0.0000000",
                            "0.0000000",
                            "0.0000000",
                            "1.0000000",
                            "0.0000000"
                        ],
                        [
                            "0.0000000",
                            "0.0000000",
                            "0.0000000",
                            "0.0000000",
                            "0.0000000",
                            "0.0000000",
                            "1.0000000"
                        ]
                    ]
                },
                {
                    "shellFunctionType": "gto",
                    "shellHarmonicType": "spherical",
                    "shellRegion": "valence",
                    "shellAngularMomentum": [
                        3
                    ],
                    "shellExponents": [
                        "10.6097000",
                        "5.2422900",
                        "2.5902400",
                        "1.2798500",
                        "0.6323800",
                        "0.2108200"
                    ],
                    "shellCoefficients": [
                        [
                            "1.0000000",
                            "0.0000000",
                            "0.0000000",
                            "0.0000000",
                            "0.0000000",
                            "0.0000000"
                        ],
                        [
                            "0.0000000",
                            "1.0000000",
                            "0.0000000",
                            "0.0000000",
                            "0.0000000",
                            "0.0000000"
                        ],
                        [
                            "0.0000000",
                            "0.0000000",
                            "1.0000000",
                            "0.0000000",
                            "0.0000000",
                            "0.0000000"
                        ],
                        [
                            "0.0000000",
                            "0.0000000",
                            "0.0000000",
                            "1.0000000",
                            "0.0000000",
                            "0.0000000"
                        ],
                        [
                            "0.0000000",
                            "0.0000000",
                            "0.0000000",
                            "0.0000000",
                            "1.0000000",
                            "0.0000000"
                        ],
                        [
                            "0.0000000",
                            "0.0000000",
                            "0.0000000",
                            "0.0000000",
                            "0.0000000",
                            "1.0000000"
                        ]
                    ]
                },
                {
                    "shellFunctionType": "gto",
                    "shellHarmonicType": "spherical",
                    "shellRegion": "valence",
                    "shellAngularMomentum": [
                        4
                    ],
                    "shellExponents": [
                        "5.8235900",
                        "3.0535100",
                        "1.6010500",
                        "0.8394900",
                        "0.2933900"
                    ],
                    "shellCoefficients": [
                        [
                            "1.0000000",
                            "0.0000000",
                            "0.0000000",
                            "0.0000000",
                            "0.0000000"
                        ],
                        [
                            "0.0000000",
                            "1.0000000",
                            "0.0000000",
                            "0.0000000",
                            "0.0000000"
                        ],
                        [
                            "0.0000000",
                            "0.0000000",
                            "1.0000000",
                            "0.0000000",
                            "0.0000000"
                        ],
                        [
                            "0.0000000",
                            "0.0000000",
                            "0.0000000",
                            "1.0000000",
                            "0.0000000"
                        ],
                        [
                            "0.0000000",
                            "0.0000000",
                            "0.0000000",
                            "0.0000000",
                            "1.0000000"
                        ]
                    ]
                },
                {
                    "shellFunctionType": "gto",
                    "shellHarmonicType": "spherical",
                    "shellRegion": "valence",
                    "shellAngularMomentum": [
                        5
                    ],
                    "shellExponents": [
                        "5.9887600",
                        "2.9543500",
                        "1.4574300",
                        "0.4894600"
                    ],
                    "shellCoefficients": [
                        [
                            "1.0000000",
                            "0.0000000",
                            "0.0000000",
                            "0.0000000"
                        ],
                        [
                            "0.0000000",
                            "1.0000000",
                            "0.0000000",
                            "0.0000000"
                        ],
                        [
                            "0.0000000",
                            "0.0000000",
                            "1.0000000",
                            "0.0000000"
                        ],
                        [
                            "0.0000000",
                            "0.0000000",
                            "0.0000000",
                            "1.0000000"
                        ]
                    ]
                },
                {
                    "shellFunctionType": "gto",
                    "shellHarmonicType": "spherical",
                    "shellRegion": "valence",
                    "shellAngularMomentum": [
                        6
                    ],
                    "shellExponents": [
                        "4.0598700",
                        "1.6950300",
                        "0.6178700"
                    ],
                    "shellCoefficients": [
                        [
                            "1.0000000",
                            "0.0000000",
                            "0.0000000"
                        ],
                        [
                            "0.0000000",
                            "1.0000000",
                            "0.0000000"
                        ],
                        [
                            "0.0000000",
                            "0.0000000",
                            "1.0000000"
                        ]
                    ]
                },
                {
                    "shellFunctionType": "gto",
                    "shellHarmonicType": "spherical",
                    "shellRegion": "valence",
                    "shellAngularMomentum": [
                        7
                    ],
                    "shellExponents": [
                        "4.1600000",
                        "1.0170000"
                    ],
                    "shellCoefficients": [
                        [
                            "1.0000000",
                            "0.0000000"
                        ],
                        [
                            "0.0000000",
                            "1.0000000"
                        ]
                    ]
                }
            ]
        }
    }
}