{
    "molssi_bse_magic": 1,
    "basisSetName": "Chipman DZP + Diffuse",
    "basisSetDescription": "DZPD    Double Zeta + Polarization + Diffuse",
    "basisSetRole": "orbital",
    "basisSetElements": {
        "1": {
            "elementEntry": "CHIPMAN.element.json"
        },
        "5": {
            "elementEntry": "CHIPMAN.element.json"
        },
        "6": {
            "elementEntry": "CHIPMAN.element.json"
        },
        "7": {
            "elementEntry": "CHIPMAN.element.json"
        },
        "8": {
            "elementEntry": "CHIPMAN.element.json"
        },
        "9": {
            "elementEntry": "CHIPMAN.element.json"
        }
    }
}